miniws4py/__init__.py
miniws4py/compat.py
miniws4py/exc.py
miniws4py/framing.py
miniws4py/messaging.py
miniws4py/streaming.py
miniws4py/utf8validator.py
miniws4py/websocket.py
miniws4py/client/__init__.py
satori/__init__.py
satori/rtm/__init__.py
satori/rtm/auth.py
satori/rtm/client.py
satori/rtm/connection.py
satori/rtm/exceptions.py
satori/rtm/internal_client.py
satori/rtm/internal_client_action.py
satori/rtm/internal_connection_miniws4py.py
satori/rtm/internal_json.py
satori/rtm/internal_logger.py
satori/rtm/internal_queue.py
satori/rtm/internal_state_machine_wrapper.py
satori/rtm/internal_subscription.py
satori/rtm/generated/__init__.py
satori/rtm/generated/client_sm.py
satori/rtm/generated/statemap.py
satori/rtm/generated/subscription_sm.py
satori_rtm_sdk-1.5.0.dist-info/DESCRIPTION.rst
satori_rtm_sdk-1.5.0.dist-info/METADATA
satori_rtm_sdk-1.5.0.dist-info/RECORD
satori_rtm_sdk-1.5.0.dist-info/WHEEL
satori_rtm_sdk-1.5.0.dist-info/metadata.json
satori_rtm_sdk-1.5.0.dist-info/top_level.txt
satori_rtm_sdk-1.5.0.dist-info/zip-safe
