Metadata-Version: 2.0
Name: satori-rtm-sdk
Version: 1.5.0
Summary: Python SDK for Satori RTM
Home-page: https://www.satori.com/
Author: Satori Worldwide, Inc.
Author-email: sdk@satori.com
License: Proprietary
Keywords: satori
Platform: UNKNOWN
Classifier: Development Status :: 5 - Production/Stable
Classifier: Intended Audience :: Developers
Classifier: License :: Other/Proprietary License
Classifier: Programming Language :: Python :: 2
Classifier: Programming Language :: Python :: 2.7
Classifier: Programming Language :: Python :: 3
Classifier: Programming Language :: Python :: 3.4
Classifier: Programming Language :: Python :: 3.5
Classifier: Programming Language :: Python :: 3.6
Requires-Dist: cbor2
Requires-Dist: certifi
Requires-Dist: enum34
Requires-Dist: six
